{
    "file": "wire\/modules\/LanguageSupport\/LanguageSupportPageNames.module",
    "textdomain": "wire--modules--languagesupport--languagesupportpagenames-module",
    "translations": {
        "ae739a236065a45c64ad51aacb19498c": {
            "text": "Aktiv?"
        },
        "35b837a5674ea74e192fc0fa8b68f46c": {
            "text": "Sidetall-prefisk for sidenavigering"
        },
        "5b5fec43bb1313c56d2e944d9567cd96": {
            "text": "Standard spr\u00e5ks hjemme-URL den samme som rot-URL?"
        },
        "6fbae724946d15c837d8d88af35ed18c": {
            "text": "Velg **Ja** om du vil at hjemmesiden til ditt standardspr\u00e5k skal bli gitt rot-URL **\/** (anbefalt). Velg **Nei** dom du vil at rot-URL skal vidersende til **\/navn\/** (hvor \/navn\/ er din hjemmesides standardspr\u00e5ks navn)."
        },
        "fccde8e7592dffb93fe985bc462771c0": {
            "text": "Denne innstillinger virker kun p\u00e5 hjemmesidens oppf\u00f8rsel. Om du velger Nei, m\u00e5 du ogs\u00e5 passe p\u00e5 at hjemmesiden har et navn definert for standard spr\u00e5k."
        },
        "ff88cd079dc8d2fb836b8807f5d266a4": {
            "text": "Ja - Rot-URL gir standard spr\u00e5ks hjemmeside (anbefalt)"
        },
        "f1bd84fbcee1b287fe538f7df1cbd700": {
            "text": "Nei - Rot-URL utf\u00f8rer vidersending til: \/navn\/"
        },
        "d5af3f8c985a3592422462cce67bc86c": {
            "text": "En s\u00f8sterside (id=%1$d) bruker allerede navnet \"%2$s\" til spr\u00e5ket: %3$s"
        },
        "68d765216e3092d42524f9f6f14ce93c": {
            "text": "Sidetallet er lagt til dette ordet i paginerte nettadresser for dette spr\u00e5ket. Hvis utelatt, vil \"%s\" brukes."
        }
    }
}